{"cameraMode":{"drawMode":0,"name":"Shaded","section":"Shading Mode"},"sceneLighting":true,"audioPlay":false,"sceneViewState":{"m_AlwaysRefresh":false,"showFog":true,"showSkybox":true,"showFlares":true,"showImageEffects":true,"showParticleSystems":true,"showVisualEffectGraphs":true,"m_FxEnabled":true},"in2DMode":false,"pivot":{"x":-46.35553741455078,"y":-325.2674560546875,"z":417.56591796875},"rotation":{"x":-0.31531357765197756,"y":0.05319806560873985,"z":-0.017707087099552156,"w":-0.9473344087600708},"size":273.3594055175781,"orthographic":false}